{
  "id": "p4-jianchi",
  "title": "坚持就是胜利",
  "level": "P4",
  "estMinutes": 4,
  "tags": ["坚持", "毅力"],
  "tokens": [
    {"char": "小", "pinyin": "xiǎo"},
    {"char": "林", "pinyin": "lín"},
    {"char": "参", "pinyin": "cān"},
    {"char": "加", "pinyin": "jiā"},
    {"char": "了", "pinyin": "le"},
    {"char": "学", "pinyin": "xué"},
    {"char": "校", "pinyin": "xiào"},
    {"char": "的", "pinyin": "de"},
    {"char": "游", "pinyin": "yóu"},
    {"char": "泳", "pinyin": "yǒng"},
    {"char": "队", "pinyin": "duì"},
    {"char": "。", "pinyin": ""},
    {"char": "刚", "pinyin": "gāng"},
    {"char": "开", "pinyin": "kāi"},
    {"char": "始", "pinyin": "shǐ"},
    {"char": "训", "pinyin": "xùn"},
    {"char": "练", "pinyin": "liàn"},
    {"char": "时", "pinyin": "shí"},
    {"char": "，", "pinyin": ""},
    {"char": "他", "pinyin": "tā"},
    {"char": "常", "pinyin": "cháng"},
    {"char": "常", "pinyin": "cháng"},
    {"char": "觉", "pinyin": "jué"},
    {"char": "得", "pinyin": "de"},
    {"char": "很", "pinyin": "hěn"},
    {"char": "累", "pinyin": "lèi"},
    {"char": "，", "pinyin": ""},
    {"char": "想", "pinyin": "xiǎng"},
    {"char": "过", "pinyin": "guò"},
    {"char": "放", "pinyin": "fàng"},
    {"char": "弃", "pinyin": "qì"},
    {"char": "。", "pinyin": ""},
    {"char": "教", "pinyin": "jiào"},
    {"char": "练", "pinyin": "liàn"},
    {"char": "告", "pinyin": "gào"},
    {"char": "诉", "pinyin": "sù"},
    {"char": "他", "pinyin": "tā"},
    {"char": "：", "pinyin": ""},
    {"char": "成", "pinyin": "chéng"},
    {"char": "功", "pinyin": "gōng"},
    {"char": "需", "pinyin": "xū"},
    {"char": "要", "pinyin": "yào"},
    {"char": "坚", "pinyin": "jiān"},
    {"char": "持", "pinyin": "chí"},
    {"char": "不", "pinyin": "bù"},
    {"char": "懈", "pinyin": "xiè"},
    {"char": "。", "pinyin": ""},
    {"char": "小", "pinyin": "xiǎo"},
    {"char": "林", "pinyin": "lín"},
    {"char": "咬", "pinyin": "yǎo"},
    {"char": "牙", "pinyin": "yá"},
    {"char": "坚", "pinyin": "jiān"},
    {"char": "持", "pinyin": "chí"},
    {"char": "下", "pinyin": "xià"},
    {"char": "来", "pinyin": "lái"},
    {"char": "，", "pinyin": ""},
    {"char": "每", "pinyin": "měi"},
    {"char": "天", "pinyin": "tiān"},
    {"char": "苦", "pinyin": "kǔ"},
    {"char": "练", "pinyin": "liàn"},
    {"char": "两", "pinyin": "liǎng"},
    {"char": "小", "pinyin": "xiǎo"},
    {"char": "时", "pinyin": "shí"},
    {"char": "。", "pinyin": ""},
    {"char": "三", "pinyin": "sān"},
    {"char": "个", "pinyin": "gè"},
    {"char": "月", "pinyin": "yuè"},
    {"char": "后", "pinyin": "hòu"},
    {"char": "，", "pinyin": ""},
    {"char": "他", "pinyin": "tā"},
    {"char": "在", "pinyin": "zài"},
    {"char": "比", "pinyin": "bǐ"},
    {"char": "赛", "pinyin": "sài"},
    {"char": "中", "pinyin": "zhōng"},
    {"char": "赢", "pinyin": "yíng"},
    {"char": "得", "pinyin": "de"},
    {"char": "了", "pinyin": "le"},
    {"char": "金", "pinyin": "jīn"},
    {"char": "牌", "pinyin": "pái"},
    {"char": "！", "pinyin": ""}
  ]
}
