{
  "id": "p5-vid-neighbors",
  "type": "video",
  "title": "关爱他人",
  "level": "P5",
  "estMinutes": 8,
  "tags": ["video", "community", "values"],
  "youtubeId": "ZFQbsN2clH8",
  "scene": "在日常生活中，我们应该主动关爱身边的人，传递温暖与正能量。",
  "hints": [
    "S 开场：简单介绍视频话题，表明你的立场",
    "C 观点：清楚说出你对关爱他人的主要看法",
    "F 感受：分享你帮助他人或被人帮助时的感受",
    "R 联系：结合你的亲身经历，举一个具体的例子",
    "A 行动：说明你会如何在生活中关爱他人",
    "S 总结：重申观点，作出结论"
  ],
  "keyElements": ["关爱", "帮助", "他人", "关怀", "温暖", "善意", "付出", "感恩", "社会", "友善"],
  "questions": [
    "你有没有主动帮助过别人？那次经历给你留下了什么印象？",
    "视频里展示了哪些关爱他人的行为？你觉得哪一种最值得学习？",
    "有人说'各家自扫门前雪'，不需要管他人的事。你同意吗？为什么？"
  ]
}
